azericard/__init__.py
azericard/__version__.py
azericard/pay.py
azericard/utils.py
azericart_django-0.0.1.dist-info/LICENSE
azericart_django-0.0.1.dist-info/METADATA
azericart_django-0.0.1.dist-info/WHEEL
azericart_django-0.0.1.dist-info/top_level.txt
azericart_django-0.0.1.dist-info/RECORD
