Metadata-Version: 2.1
Name: azericart-django
Version: 0.0.1
Summary: Django ucun standart azericard odenis kitabxanasi
Home-page: https://github.com/CavidRzayev/Azericard
Author: Cavid Rzayev
Author-email: rzayev592@gmail.com
License: UNKNOWN
Platform: UNKNOWN
Classifier: Programming Language :: Python :: 3
Classifier: License :: OSI Approved :: MIT License
Classifier: Operating System :: OS Independent
Requires-Python: >=3.6
Requires-Dist: requests
